csv_bleach/__init__.py
csv_bleach/__main__.py
csv_bleach/detect_delimiter.py
csv_bleach/detect_row_count.py
csv_bleach/line_decoder.py
csv_bleach/line_parser.py
csv_bleach/type_casting.py
csv_bleach-2.4.0.dist-info/LICENSE
csv_bleach-2.4.0.dist-info/METADATA
csv_bleach-2.4.0.dist-info/WHEEL
csv_bleach-2.4.0.dist-info/entry_points.txt
csv_bleach-2.4.0.dist-info/RECORD
