Metadata-Version: 2.1
Name: csv_bleach
Version: 2.4.0
Summary: clean CSVs
Home-page: https://github.com/gecBurton/csv-bleach
License: MIT
Keywords: csv
Author: George Burton
Author-email: g.e.c.burton@gmail.com
Requires-Python: >=3.9.0
Classifier: License :: OSI Approved :: MIT License
Classifier: Programming Language :: Python :: 3
Classifier: Programming Language :: Python :: 3.9
Classifier: Programming Language :: Python :: 3.10
Classifier: Programming Language :: Python :: 3.11
Classifier: Programming Language :: Python :: 3.12
Classifier: Topic :: Text Processing
Requires-Dist: charset-normalizer (<=3.3.0)
Requires-Dist: click (>=8.1.3,<9.0.0)
Project-URL: Repository, https://github.com/gecBurton/csv-bleach
